cmake_language_server-0.1.10.dist-info/METADATA
cmake_language_server-0.1.10.dist-info/WHEEL
cmake_language_server-0.1.10.dist-info/entry_points.txt
cmake_language_server-0.1.10.dist-info/licenses/LICENSE
cmake_language_server/__init__.py
cmake_language_server/api.py
cmake_language_server/server.py
cmake_language_server/version.py
cmake_language_server-0.1.10.dist-info/RECORD
