Metadata-Version: 2.1
Name: cmake-language-server
Version: 0.1.10
Summary: CMake LSP Implementation
Keywords: cmake,completion,vim,lsp
Author: Regen
License: MIT
Classifier: Development Status :: 3 - Alpha
Classifier: Environment :: Console
Classifier: Intended Audience :: Developers
Classifier: Operating System :: OS Independent
Classifier: Topic :: Software Development
Classifier: Topic :: Text Editors :: Integrated Development Environments (IDE)
Classifier: Topic :: Utilities
Project-URL: Repository, https://github.com/regen100/cmake-language-server
Requires-Python: <3.13,>=3.8.0
Requires-Dist: pygls>=1.1.1
